wspay/__init__.py
wspay/apps.py
wspay/conf.py
wspay/forms.py
wspay/models.py
wspay/services.py
wspay/signals.py
wspay/urls.py
wspay/views.py
wspay/migrations/0001_initial.py
wspay/migrations/0002_wspaytransaction_wspayrequest_transactions.py
wspay/migrations/0003_rename_wspaytransaction_transactionhistory_and_more.py
wspay/migrations/0004_remove_wspayrequest_transactions.py
wspay/migrations/__init__.py
wspay/templates/wspay/error.html
wspay/templates/wspay/test.html
wspay/templates/wspay/wspay_submit.html
wspay/tests/__init__.py
wspay/tests/settings.py
wspay/tests/test_wspay.py
wspay/tests/urls.py
wspay/tests/utils.py
django_wspay-0.3.7.dist-info/LICENSE.txt
django_wspay-0.3.7.dist-info/METADATA
django_wspay-0.3.7.dist-info/WHEEL
django_wspay-0.3.7.dist-info/top_level.txt
django_wspay-0.3.7.dist-info/RECORD
